ltron/__init__.py
ltron/authors.py
ltron/compression.py
ltron/config.py
ltron/evaluation.py
ltron/exceptions.py
ltron/hierarchy.py
ltron/home.py
ltron/installation.py
ltron/license.py
ltron/matching.py
ltron/score.py
ltron/settings.py
ltron/utils.py
ltron/blender/__init__.py
ltron/blender/batch_export.py
ltron/blender/export_obj.py
ltron/bricks/__init__.py
ltron/bricks/brick_color.py
ltron/bricks/brick_instance.py
ltron/bricks/brick_scene.py
ltron/bricks/brick_shape.py
ltron/bricks/snap.py
ltron/dataset/__init__.py
ltron/dataset/break_and_make.py
ltron/dataset/build_dataset.py
ltron/dataset/carbon_star.py
ltron/dataset/cars.py
ltron/dataset/conditional_snap_two.py
ltron/dataset/connection2d.py
ltron/dataset/count_tt3.py
ltron/dataset/dataset_analysis.py
ltron/dataset/dataset_stats.py
ltron/dataset/get_max_snaps.py
ltron/dataset/lte_500.py
ltron/dataset/metadata.py
ltron/dataset/micro_wheels.py
ltron/dataset/old_dataset.py
ltron/dataset/part_usage.py
ltron/dataset/parts.py
ltron/dataset/paths.py
ltron/dataset/rando_micro_wheels.py
ltron/dataset/random_construction.py
ltron/dataset/random_stack.py
ltron/dataset/scales.py
ltron/dataset/session_to_generate_data.py
ltron/dataset/small_vehicles.py
ltron/dataset/snap_four.py
ltron/dataset/snap_one.py
ltron/dataset/sub_assemblies.py
ltron/dataset/submodel_extraction.py
ltron/dataset/tiny_turbos.py
ltron/dataset/tiny_turbos2.py
ltron/dataset/tiny_turbos3.py
ltron/dataset/tt3_subassemblies.py
ltron/dataset/vehicles.py
ltron/dataset/datastructure/__init__.py
ltron/dataset/datastructure/connected_components.py
ltron/dataset/omr_clean/__init__.py
ltron/dataset/omr_clean/annotation_tester.py
ltron/dataset/omr_clean/blacklist.py
ltron/dataset/omr_clean/brick_variants.py
ltron/dataset/omr_clean/dataset_annotation.py
ltron/dataset/omr_clean/ultimate_cleanup.py
ltron/geometry/__init__.py
ltron/geometry/collision.py
ltron/geometry/collision_sampler.py
ltron/geometry/deduplicate_spatial.py
ltron/geometry/epsilon_array.py
ltron-1.0.2.dist-info/LICENSE
ltron-1.0.2.dist-info/METADATA
ltron-1.0.2.dist-info/WHEEL
ltron-1.0.2.dist-info/entry_points.txt
ltron-1.0.2.dist-info/top_level.txt
ltron-1.0.2.dist-info/RECORD
