Metadata-Version: 2.1
Name: ltron
Version: 1.0.2
Summary: LEGO interactive machine learning environment.
Home-page: https://github.com/aaronwalsman/ltron
Author: Aaron Walsman
Author-email: aaronwalsman@gmail.com
Classifier: Programming Language :: Python :: 3
Classifier: License :: OSI Approved :: MIT License
Classifier: Operating System :: OS Independent
License-File: LICENSE
Requires-Dist: gym (==0.17.3)
Requires-Dist: numpy
Requires-Dist: scipy
Requires-Dist: pyquaternion
Requires-Dist: gdown
Requires-Dist: tqdm
Requires-Dist: splendor-render
